mcp_server_dexscreener/__init__.py
mcp_server_dexscreener/__main__.py
mcp_server_dexscreener/server.py
mcp_server_dexscreener-0.6.2.dist-info/METADATA
mcp_server_dexscreener-0.6.2.dist-info/WHEEL
mcp_server_dexscreener-0.6.2.dist-info/entry_points.txt
mcp_server_dexscreener-0.6.2.dist-info/licenses/LICENCE
mcp_server_dexscreener-0.6.2.dist-info/RECORD
